lunar_perigees/__init__.py
lunar_perigees/lunar_perigees.py
lunar_perigees-0.0.5.dist-info/METADATA
lunar_perigees-0.0.5.dist-info/WHEEL
lunar_perigees-0.0.5.dist-info/licenses/LICENSE
lunar_perigees-0.0.5.dist-info/RECORD
