Metadata-Version: 2.3
Name: lunar_perigees
Version: 0.0.5
Summary: finds monthly lunar perigees
Project-URL: Homepage, https://github.com/jayschoen/lunar_perigees
Project-URL: Issues, https://github.com/jayschoen/lunar_perigees/issues
Author-email: Jay Schoen <jay.r.schoen@gmail.com>
License-File: LICENSE
Requires-Python: >=3.9
Requires-Dist: requests
Requires-Dist: scipy
